{
	"animations": [
		{
			"offsets": [
				0,
				0
			],
			"loop": false,
			"fps": 24,
			"anim": "idle",
			"indices": [],
			"name": "idle"
		},
		{
			"loop": false,
			"offsets": [
				0,
				-6
			],
			"anim": "hey",
			"fps": 24,
			"name": "hey",
			"indices": []
		},
		{
			"loop": false,
			"offsets": [
				-28,
				-4
			],
			"anim": "dodge",
			"fps": 24,
			"name": "dodge",
			"indices": []
		},
		{
			"offsets": [
				-27,
				-6
			],
			"loop": false,
			"fps": 24,
			"anim": "singLEFT",
			"indices": [
				0,
				1,
				2,
				3
			],
			"name": "left"
		},
		{
			"offsets": [
				-33,
				7
			],
			"loop": false,
			"fps": 24,
			"anim": "singUP",
			"indices": [
				0,
				1,
				2,
				3
			],
			"name": "up"
		},
		{
			"offsets": [
				-31,
				-19
			],
			"loop": false,
			"fps": 24,
			"anim": "singDOWN",
			"indices": [
				0,
				1,
				2,
				3
			],
			"name": "down"
		},
		{
			"offsets": [
				130,
				-6
			],
			"loop": false,
			"fps": 24,
			"anim": "singRIGHT",
			"indices": [
				0,
				1,
				2,
				3
			],
			"name": "right"
		},
		{
			"offsets": [
				-60,
				-110
			],
			"loop": false,
			"fps": 24,
			"anim": "singLEFTmiss",
			"indices": [],
			"name": "left miss"
		},
		{
			"loop": false,
			"offsets": [
				-20,
				-55
			],
			"anim": "singDOWNmiss",
			"fps": 24,
			"name": "down miss",
			"indices": []
		},
		{
			"loop": false,
			"offsets": [
				-40,
				-100
			],
			"anim": "singUPmiss",
			"fps": 24,
			"name": "up miss",
			"indices": []
		},
		{
			"loop": false,
			"offsets": [
				-39,
				-70
			],
			"anim": "singRIGHTmiss",
			"fps": 24,
			"name": "right miss",
			"indices": []
		}
	],
	"no_antialiasing": false,
	"image": "characters/lad",
	"position": [
		0,
		300
	],
	"healthicon": "lad",
	"flip_x": true,
	"healthbar_colors": [
		16,
		2,
		205
	],
	"camera_position": [
		0,
		0
	],
	"sing_duration": 6.1,
	"scale": 1
}